sil_sdk/__init__.py
sil_sdk/client/__init__.py
sil_sdk/client/dag_async_client.py
sil_sdk/client/sar_async_client.py
sil_sdk/client/vis_async_client.py
sil_sdk/modules/__init__.py
sil_sdk/modules/dag.py
sil_sdk/modules/sar.py
sil_sdk/modules/vis.py
sil_sdk-0.1.7.dist-info/LICENSE
sil_sdk-0.1.7.dist-info/METADATA
sil_sdk-0.1.7.dist-info/WHEEL
sil_sdk-0.1.7.dist-info/top_level.txt
sil_sdk-0.1.7.dist-info/RECORD
