Metadata-Version: 2.1
Name: sil-sdk
Version: 0.1.7
Summary: SIL Robotics SDK for SAR grippers, DAG hands, and VIS systems over WebSockets
Author-email: Kaivalya <your_email@example.com>
License: Proprietary - Sastra Innovation Labs
Project-URL: Homepage, https://github.com/Kaivalya192/sil-sdk
Project-URL: Documentation, https://github.com/Kaivalya192/sil-sdk/wiki
Requires-Python: >=3.7
License-File: LICENSE
Requires-Dist: websockets
Requires-Dist: numpy
Requires-Dist: opencv-python
